RSIM/__init__.py
RSIM/config.py
RSIM/bootstrap/__init__.py
RSIM/bootstrap/bootstrap_ci.py
RSIM/bootstrap/cross_validation.py
RSIM/bootstrap/jackknife.py
RSIM/bootstrap/permutation_tests.py
RSIM/core/base.py
RSIM/core/manager.py
RSIM/financial/__init__.py
RSIM/financial/interest_rate_models.py
RSIM/financial/option_pricing.py
RSIM/financial/portfolio.py
RSIM/financial/var_estimation.py
RSIM/inventory/__init__.py
RSIM/inventory/eoq.py
RSIM/inventory/newsvendor.py
RSIM/inventory/sq_policy.py
RSIM/inventory/ss_policy.py
RSIM/markov_chains/__init__.py
RSIM/markov_chains/continuous_markov.py
RSIM/markov_chains/discrete_markov.py
RSIM/markov_chains/hidden_markov.py
RSIM/markov_chains/markov_chain_test.py
RSIM/markov_chains/mcmc.py
RSIM/monte_carlo/__init__.py
RSIM/monte_carlo/integration.py
RSIM/monte_carlo/monte_carlo_test.py
RSIM/monte_carlo/option_pricing.py
RSIM/monte_carlo/pi_estimation.py
RSIM/monte_carlo/random_walk.py
RSIM/networks/__init__.py
RSIM/networks/epidemic_models.py
RSIM/networks/random_graphs.py
RSIM/networks/social_networks.py
RSIM/networks/traffic_simulation.py
RSIM/optimization/__init__.py
RSIM/optimization/genetic_algorithm.py
RSIM/optimization/particle_swarm.py
RSIM/optimization/response_surface.py
RSIM/optimization/simulated_annealing.py
RSIM/queueing/__init__.py
RSIM/queueing/mg1_queue.py
RSIM/queueing/mm1_queue.py
RSIM/queueing/mmk_queue.py
RSIM/queueing/network_queues.py
RSIM/reliability/__init__.py
RSIM/reliability/component_reliability.py
RSIM/reliability/failure_analysis.py
RSIM/reliability/maintenance_models.py
RSIM/reliability/system_reliability.py
RSIM/survival/__init__.py
RSIM/survival/cox_regression.py
RSIM/survival/exponential_survival.py
RSIM/survival/kaplan_meier.py
RSIM/survival/parametric_survival.py
RSIM/ui/__init__.py
RSIM/variance_reduction/__init__.py
RSIM/variance_reduction/antithetic_variables.py
RSIM/variance_reduction/control_variates.py
RSIM/variance_reduction/importance_sampling.py
rsim-1.0.0.dist-info/licenses/LICENSE
rsim-1.0.0.dist-info/METADATA
rsim-1.0.0.dist-info/WHEEL
rsim-1.0.0.dist-info/top_level.txt
rsim-1.0.0.dist-info/RECORD
