Metadata-Version: 2.4
Name: RSIM
Version: 1.0.0
Summary: A Python package for different simulation approaches
Author: SimLib Team
Author-email: Reza Shahriari <rezshahriari@gmail.com>
License: MIT License
Project-URL: Homepage, https://github.com/reza-shahriari/RSIM
Project-URL: Bug Reports, https://github.com/reza-shahriari/RSIM/issues
Project-URL: Source, https://github.com/reza-shahriari/RSIM
Classifier: Development Status :: 3 - Alpha
Classifier: Intended Audience :: Financial and Insurance Industry
Classifier: License :: OSI Approved :: MIT License
Classifier: Programming Language :: Python :: 3
Classifier: Programming Language :: Python :: 3.8
Classifier: Programming Language :: Python :: 3.9
Classifier: Programming Language :: Python :: 3.10
Classifier: Programming Language :: Python :: 3.11
Requires-Python: >=3.8
License-File: LICENSE
Requires-Dist: pandas>=1.3.0
Requires-Dist: numpy>=1.21.0
Requires-Dist: matplotlib>=3.5.0
Requires-Dist: scipy>=1.7.0
Dynamic: author
Dynamic: license-file
Dynamic: requires-python
